examples/example.py
python_cli_generator/__init__.py
python_cli_generator/cli.py
python_cli_generator/cli_builtin.py
python_cli_generator/cli_generator.py
python_cli_generator/input_processor.py
python_cli_generator/output_printer.py
python_cli_generator/output_processor.py
python_cli_generator/parsing_processor.py
python_cli_generator/utils.py
python_cli_generator/plugins/__init__.py
python_cli_generator/plugins/cache.py
python_cli_generator/plugins/http.py
python_cli_generator-0.2.3.dist-info/LICENSE.md
python_cli_generator-0.2.3.dist-info/METADATA
python_cli_generator-0.2.3.dist-info/WHEEL
python_cli_generator-0.2.3.dist-info/top_level.txt
python_cli_generator-0.2.3.dist-info/RECORD
