Metadata-Version: 2.1
Name: python-cli-generator
Version: 0.2.3
Summary: A library that allows a rapid creation of a CLI by automatically reading the attributes and parameters inside a class and generating its corresponding Command Line Interface.
Home-page: https://github.com/AlexSua/python-cli-generator
Author: Alejandro Suárez
Author-email: alejandrosuarez.eu@gmail.com
License: MIT
Keywords: python cli generator class output parsing
Classifier: Development Status :: 3 - Alpha
Classifier: Topic :: Utilities
Classifier: License :: OSI Approved :: BSD License
Requires-Python: >=3.7
License-File: LICENSE.md
